here_search/polyline_converter/__init__.py
here_search/polyline_converter/decoding.py
here_search/polyline_converter/encoding.py
here_polyline_converter-0.2.1.dist-info/LICENSE
here_polyline_converter-0.2.1.dist-info/METADATA
here_polyline_converter-0.2.1.dist-info/WHEEL
here_polyline_converter-0.2.1.dist-info/top_level.txt
here_polyline_converter-0.2.1.dist-info/RECORD
