Metadata-Version: 2.1
Name: here-polyline-converter
Version: 0.2.1
Summary: A tool to convert strings between HERE Flexible Polyline format and the (now legacy) format used in HERE Places API
Home-page: https://here.com
Author: HERE Europe B.V.
Author-email: emmanuel.decitre@here.com
License: The MIT License
Project-URL: Bug Tracker, https://github.com/heremaps/here-polyline-converter/issues
Project-URL: Source, https://github.com/heremaps/here-polyline-converter
Keywords: HERE,Search,Polyline,GS7
Platform: any
Classifier: Development Status :: 4 - Beta
Classifier: Intended Audience :: Developers
Classifier: Programming Language :: Python :: 3 :: Only
Classifier: Programming Language :: Python :: 3.7
Classifier: Programming Language :: Python :: 3.8
Classifier: Programming Language :: Python :: 3.9
Classifier: Programming Language :: Python :: 3.10
Classifier: License :: OSI Approved :: MIT License
Requires-Python: >=3.7
License-File: LICENSE
Requires-Dist: flexpolyline
